nejma/__init__.py
nejma/__version__.py
nejma/layers.py
nejma/ext/__init__.py
nejma/ext/starlette/__init__.py
nejma/ext/starlette/endpoints.py
tests/__init__.py
nejma-0.1.0.dist-info/LICENSE.md
nejma-0.1.0.dist-info/METADATA
nejma-0.1.0.dist-info/WHEEL
nejma-0.1.0.dist-info/top_level.txt
nejma-0.1.0.dist-info/RECORD
