Metadata-Version: 2.1
Name: nejma
Version: 0.1.0
Summary: Talk realtime with groups
Home-page: https://github.com/taoufik07/nejma
Author: Taoufik Abbassid
Author-email: abacidtaoufik@gmail.com
License: BSD
Platform: UNKNOWN
Classifier: Environment :: Web Environment
Classifier: Intended Audience :: Developers
Classifier: License :: OSI Approved :: BSD License
Classifier: Operating System :: OS Independent
Classifier: Programming Language :: Python :: 3
Classifier: Programming Language :: Python :: 3.6
Classifier: Programming Language :: Python :: 3.7
Requires-Python: >=3.6
